nkdw_maru/__init__.py
nkdw_maru/dw.py
nkdw_maru/dwlib.py
nkdw_maru/files.py
nkdw_maru-1.0.1.dist-info/LICENSE
nkdw_maru-1.0.1.dist-info/METADATA
nkdw_maru-1.0.1.dist-info/WHEEL
nkdw_maru-1.0.1.dist-info/entry_points.txt
nkdw_maru-1.0.1.dist-info/RECORD
