Metadata-Version: 2.3
Name: nkdw_maru
Version: 1.0.1
Summary: File and package backup for dnf and flatpak. Saves to a single yaml file for the lulz
License: GPL-3.0-or-later
Author: maru
Author-email: maru@lithium-dev.xyz
Classifier: License :: OSI Approved :: GNU General Public License v3 or later (GPLv3+)
Classifier: Programming Language :: Python :: 2
Classifier: Programming Language :: Python :: 2.7
Classifier: Programming Language :: Python :: 3
Classifier: Programming Language :: Python :: 3.4
Classifier: Programming Language :: Python :: 3.5
Classifier: Programming Language :: Python :: 3.6
Classifier: Programming Language :: Python :: 3.7
Classifier: Programming Language :: Python :: 3.8
Classifier: Programming Language :: Python :: 3.9
Classifier: Programming Language :: Python :: 3.10
Classifier: Programming Language :: Python :: 3.11
Classifier: Programming Language :: Python :: 3.12
Classifier: Programming Language :: Python :: 3.13
Requires-Dist: click
Requires-Dist: requests
Project-URL: Homepage, https://www.github.com/marufromhell/nkdw
Project-URL: Repository, https://www.github.com/marufromhell/nkdw
